LICENSE
influxdb_flask/__init__.py
influxdb_flask/influxdb_flask.py
influxdb_flask-0.1.2.dist-info/LICENSE
influxdb_flask-0.1.2.dist-info/WHEEL
influxdb_flask-0.1.2.dist-info/METADATA
influxdb_flask-0.1.2.dist-info/RECORD
