Metadata-Version: 2.1
Name: influxdb-flask
Version: 0.1.2
Summary: InfluxDB-Flask adds influxdb-client-python support to Flask.
Home-page: https://github.com/simon7426/InfluxDB-Flask
License: BSD-3-Clause
Keywords: Flask,InfluxDB
Author: simon.islam
Author-email: mail@simonislam.com
Requires-Python: >=3.7,<4.0
Classifier: License :: OSI Approved :: BSD License
Classifier: Programming Language :: Python :: 3
Classifier: Programming Language :: Python :: 3.10
Classifier: Programming Language :: Python :: 3.7
Classifier: Programming Language :: Python :: 3.8
Classifier: Programming Language :: Python :: 3.9
Requires-Dist: Flask (>=2.0.3,<3.0.0)
Requires-Dist: influxdb-client (>=1.25.0,<2.0.0)
Project-URL: Documentation, https://influxdb-flask.readthedocs.io/en/latest/
Project-URL: Repository, https://github.com/simon7426/InfluxDB-Flask
Project-URL: issues, https://github.com/simon7426/InfluxDB-Flask/issues
